{
  "name": "skeleton",
  "width": 32,
  "height": 32,
  "commands": [
    { "type": "drawRect", "args": [0.25, 0.0, 0.15, 0.25, 0, 0], "color": "#e0e0d0", "filled": true },
    { "type": "drawRect", "args": [0.6, 0.0, 0.15, 0.25, 0, 0], "color": "#e0e0d0", "filled": true },
    { "type": "drawRect", "args": [0.2, 0.25, 0.6, 0.08, 0, 0], "color": "#d0d0c0", "filled": true },
    { "type": "drawRect", "args": [0.3, 0.25, 0.4, 0.3, 0, 0], "color": "#e8e8d8", "filled": true },
    { "type": "drawRect", "args": [0.35, 0.35, 0.3, 0.04, 0, 0], "color": "#222222", "filled": true },
    { "type": "drawRect", "args": [0.35, 0.42, 0.3, 0.04, 0, 0], "color": "#222222", "filled": true },
    { "type": "drawRect", "args": [0.08, 0.32, 0.22, 0.1, 0, 0], "color": "#d8d8c8", "filled": true },
    { "type": "drawRect", "args": [0.7, 0.32, 0.22, 0.1, 0, 0], "color": "#d8d8c8", "filled": true },
    { "type": "drawCircle", "args": [0.5, 0.7, 0.17, 0, 0], "color": "#f0f0e0", "segments": 16, "filled": true },
    { "type": "drawCircle", "args": [0.4, 0.72, 0.05, 0, 0], "color": "#880000", "segments": 8, "filled": true },
    { "type": "drawCircle", "args": [0.6, 0.72, 0.05, 0, 0], "color": "#880000", "segments": 8, "filled": true },
    { "type": "drawRect", "args": [0.38, 0.6, 0.24, 0.04, 0, 0], "color": "#222222", "filled": true }
  ]
}
